hi_sooj1n/__init__.py
hi_sooj1n/hello.py
hi_sooj1n-0.7.0.dist-info/METADATA
hi_sooj1n-0.7.0.dist-info/WHEEL
hi_sooj1n-0.7.0.dist-info/entry_points.txt
hi_sooj1n-0.7.0.dist-info/top_level.txt
hi_sooj1n-0.7.0.dist-info/RECORD
