Metadata-Version: 2.1
Name: hi_sooj1n
Version: 0.7.0
Summary: Default template for PDM package
Author-email: sooj1n <sujin19371@gmail.com>
License: MIT
Requires-Python: ==3.12.*
